encfile/__init__.py
FileEncTool-1.5.dist-info/LICENSE
FileEncTool-1.5.dist-info/METADATA
FileEncTool-1.5.dist-info/WHEEL
FileEncTool-1.5.dist-info/top_level.txt
FileEncTool-1.5.dist-info/RECORD
