Metadata-Version: 2.1
Name: FileEncTool
Version: 1.5
Summary: File Encryption Tool——A powerful asymmetric file encryption Python library.
Home-page: https://github.com/MWCT-Technicalization-Organization/File_Encryption_Tool
Author: 核善的小兲
Author-email: to@mwtour.cn
License: AGPL3.0
License-File: LICENSE
Requires-Dist: pycryptodome
Requires-Dist: tqdm
